valid_model/__init__.py
valid_model/base.py
valid_model/descriptors.py
valid_model/exc.py
valid_model/utils.py
valid_model/validators.py
valid_model-0.4.0.dist-info/DESCRIPTION.rst
valid_model-0.4.0.dist-info/METADATA
valid_model-0.4.0.dist-info/RECORD
valid_model-0.4.0.dist-info/WHEEL
valid_model-0.4.0.dist-info/entry_points.txt
valid_model-0.4.0.dist-info/metadata.json
valid_model-0.4.0.dist-info/top_level.txt
