Metadata-Version: 2.0
Name: valid-model
Version: 0.4.0
Summary: Generic data modeling and validation
Home-page: https://github.com/yoshrote/valid_model
Author: Joshua Forman
Author-email: josh@yoshrote.com
License: MIT
Platform: UNKNOWN
Classifier: Intended Audience :: Developers
Classifier: License :: OSI Approved :: MIT License
Classifier: Programming Language :: Python :: 2.7
Classifier: Programming Language :: Python :: 3.2
Classifier: Programming Language :: Python :: 3.3
Classifier: Programming Language :: Python :: 3.4
Classifier: Programming Language :: Python :: 3.5
Classifier: Programming Language :: Python :: 3.6
Requires-Dist: six
